MANIFEST.in
README.md
requirements.txt
setup.py
wesanderson/__init__.py
wesanderson/__package_info__.py
wesanderson.egg-info/PKG-INFO
wesanderson.egg-info/SOURCES.txt
wesanderson.egg-info/dependency_links.txt
wesanderson.egg-info/top_level.txt