Metadata-Version: 2.4
Name: wesanderson
Version: 0.0.4
Summary: color palettes from Wes Anderson films, based on Karthik Ram's R version.
Home-page: 
Author: Hunter Wapman
Author-email: hunter.wapman@gmail.com
Keywords: color,wesanderson
Classifier: Programming Language :: Python :: 3
Classifier: License :: OSI Approved :: GNU General Public License v3 or later (GPLv3+)
Classifier: Operating System :: OS Independent
Classifier: Natural Language :: English
Dynamic: author
Dynamic: author-email
Dynamic: classifier
Dynamic: description
Dynamic: description-content-type
Dynamic: keywords
Dynamic: summary
